uv_upsync/__init__.py
uv_upsync/__main__.py
uv_upsync/commands.py
uv_upsync/exceptions.py
uv_upsync/logging.py
uv_upsync/parsers.py
uv_upsync/pypi.py
uv_upsync/uv.py
uv_upsync-2.1.0.dist-info/METADATA
uv_upsync-2.1.0.dist-info/WHEEL
uv_upsync-2.1.0.dist-info/entry_points.txt
uv_upsync-2.1.0.dist-info/licenses/LICENSE
uv_upsync-2.1.0.dist-info/RECORD
