Metadata-Version: 2.4
Name: uv-upsync
Version: 2.1.0
Summary: uv-upsync - is a tool for automated dependency updates and version bumping in pyproject.toml.
Project-URL: Homepage, https://github.com/pivoshenko/uv-upsync
Project-URL: Repository, https://github.com/pivoshenko/uv-upsync
Author-email: Volodymyr Pivoshenko <volodymyr.pivoshenko@gmail.com>
Maintainer-email: Volodymyr Pivoshenko <volodymyr.pivoshenko@gmail.com>
License-Expression: MIT
License-File: LICENSE
Keywords: cli,cli-tool,cli-tools,cross-platform,dependencies,dependencies-management,dependencies-update,dependencies-upgrade,dependency,hacktoberfest,packaging,packaging-management,packaging-update,packaging-upgrade,plugin,plugins,pypi,python,uv,uv-plugin,uv-plugins
Classifier: Development Status :: 5 - Production/Stable
Classifier: Environment :: Other Environment
Classifier: Intended Audience :: Developers
Classifier: Intended Audience :: Information Technology
Classifier: License :: OSI Approved :: MIT License
Classifier: Natural Language :: English
Classifier: Operating System :: OS Independent
Classifier: Programming Language :: Python
Classifier: Programming Language :: Python :: 3
Classifier: Programming Language :: Python :: 3.9
Classifier: Programming Language :: Python :: 3.10
Classifier: Programming Language :: Python :: 3.11
Classifier: Programming Language :: Python :: 3.12
Classifier: Programming Language :: Python :: 3.13
Classifier: Topic :: Scientific/Engineering
Classifier: Topic :: Software Development
Classifier: Topic :: Software Development :: Libraries
Classifier: Topic :: Software Development :: Libraries :: Python Modules
Requires-Python: >=3.10
Requires-Dist: click>=8.1.8
Requires-Dist: httpx>=0.28.1
Requires-Dist: tomlkit>=0.13.3
